{
	"info": {
		"_postman_id": "1c18c25e-882e-401d-92ee-edfca2910093",
		"name": "webcodino",
		"schema": "https://schema.getpostman.com/json/collection/v2.1.0/collection.json",
		"_exporter_id": "30950862",
		"_collection_link": "https://supportchat.postman.co/workspace/My-Workspace~7bfe59cd-a242-4787-829c-0008acab9ac3/collection/30950862-1c18c25e-882e-401d-92ee-edfca2910093?action=share&source=collection_link&creator=30950862"
	},
	"item": [
		{
			"name": "auth",
			"item": [
				{
					"name": "register",
					"request": {
						"method": "POST",
						"header": [],
						"body": {
							"mode": "raw",
							"raw": "{\r\n    \"name\": \"امیرمهدی شجاعی کیان\",\r\n    \"email\": \"amir@gmail.com\",\r\n    \"password\": \"123456\",\r\n    \"phone\": \"09030882522\"\r\n}",
							"options": {
								"raw": {
									"language": "json"
								}
							}
						},
						"url": {
							"raw": "https://cw4sok48swgwsc4skokoook4.37.27.187.127.sslip.io/api/auth/register",
							"protocol": "http",
							"host": [
								"localhost"
							],
							"port": "5000",
							"path": [
								"api",
								"auth",
								"register"
							]
						}
					},
					"response": []
				},
				{
					"name": "login",
					"request": {
						"method": "POST",
						"header": [],
						"body": {
							"mode": "raw",
							"raw": "{\r\n  \"identifier\": \"amsh@gmail.com\",\r\n  \"password\": \"1234567\"\r\n}",
							"options": {
								"raw": {
									"language": "json"
								}
							}
						},
						"url": {
							"raw": "https://cw4sok48swgwsc4skokoook4.37.27.187.127.sslip.io/api/auth/login",
							"protocol": "http",
							"host": [
								"localhost"
							],
							"port": "5000",
							"path": [
								"api",
								"auth",
								"login"
							]
						}
					},
					"response": []
				},
				{
					"name": "checkToken",
					"request": {
						"auth": {
							"type": "bearer",
							"bearer": [
								{
									"key": "token",
									"value": "eyJhbGciOiJIUzI1NiIsInR5cCI6IkpXVCJ9.eyJfaWQiOiI2OGEwOWI4MWM4MTMzYjNmOTFjZDk2ZDYiLCJpYXQiOjE3NTUzNTYyMDIsImV4cCI6MTc1NTQ0MjYwMn0.fiaUyRy_lNkFFsHWTQPyap59Qa58IgC3_3BFGUDtEUg",
									"type": "string"
								}
							]
						},
						"method": "GET",
						"header": [],
						"url": {
							"raw": "https://cw4sok48swgwsc4skokoook4.37.27.187.127.sslip.io/api/auth/me",
							"protocol": "http",
							"host": [
								"localhost"
							],
							"port": "5000",
							"path": [
								"api",
								"auth",
								"me"
							]
						}
					},
					"response": []
				},
				{
					"name": "logout",
					"request": {
						"auth": {
							"type": "bearer",
							"bearer": [
								{
									"key": "token",
									"value": "eyJhbGciOiJIUzI1NiIsInR5cCI6IkpXVCJ9.eyJfaWQiOiI2OGEwOWI4MWM4MTMzYjNmOTFjZDk2ZDYiLCJpYXQiOjE3NTUzNTYxMzMsImV4cCI6MTc1NTQ0MjUzM30.GeWJ-8FQFgQG44dBTdc9L_FZRO8m2_hixlbHNdL3gts",
									"type": "string"
								}
							]
						},
						"method": "POST",
						"header": [],
						"url": {
							"raw": "https://cw4sok48swgwsc4skokoook4.37.27.187.127.sslip.io/api/auth/logout",
							"protocol": "http",
							"host": [
								"localhost"
							],
							"port": "5000",
							"path": [
								"api",
								"auth",
								"logout"
							]
						}
					},
					"response": []
				},
				{
					"name": "resetPassword",
					"request": {
						"auth": {
							"type": "bearer",
							"bearer": [
								{
									"key": "token",
									"value": "eyJhbGciOiJIUzI1NiIsInR5cCI6IkpXVCJ9.eyJfaWQiOiI2OGEwOWI4MWM4MTMzYjNmOTFjZDk2ZDYiLCJpYXQiOjE3NTUzNTYyMDIsImV4cCI6MTc1NTQ0MjYwMn0.fiaUyRy_lNkFFsHWTQPyap59Qa58IgC3_3BFGUDtEUg",
									"type": "string"
								}
							]
						},
						"method": "PUT",
						"header": [],
						"body": {
							"mode": "raw",
							"raw": "{\r\n    \"newPassword\":\"1234567\"\r\n}",
							"options": {
								"raw": {
									"language": "json"
								}
							}
						},
						"url": {
							"raw": "https://cw4sok48swgwsc4skokoook4.37.27.187.127.sslip.io/api/auth/change-password",
							"protocol": "http",
							"host": [
								"localhost"
							],
							"port": "5000",
							"path": [
								"api",
								"auth",
								"change-password"
							]
						}
					},
					"response": []
				}
			]
		},
		{
			"name": "tickets",
			"item": [
				{
					"name": "Create Ticket",
					"request": {
						"auth": {
							"type": "bearer",
							"bearer": [
								{
									"key": "token",
									"value": "{{authToken}}",
									"type": "string"
								}
							]
						},
						"method": "POST",
						"header": [],
						"body": {
							"mode": "raw",
							"raw": "{\r\n    \"title\": \"مشکل\",\r\n    \"description\": \"هخسیتعارخس\",\r\n    \"status\": \"open\",\r\n    \"priority\": \"low\",\r\n    \"department\": \"Technical Support\",\r\n    \"message\": \"سلام\"\r\n    // \"attachments\": \"\"\r\n}",
							"options": {
								"raw": {
									"language": "json"
								}
							}
						},
						"url": {
							"raw": "https://cw4sok48swgwsc4skokoook4.37.27.187.127.sslip.io/api/tickets/add",
							"protocol": "http",
							"host": [
								"localhost"
							],
							"port": "5000",
							"path": [
								"api",
								"tickets",
								"add"
							]
						}
					},
					"response": []
				},
				{
					"name": "Get All Tickets for user",
					"request": {
						"auth": {
							"type": "bearer",
							"bearer": [
								{
									"key": "token",
									"value": "{{authToken}}",
									"type": "string"
								}
							]
						},
						"method": "GET",
						"header": [],
						"url": {
							"raw": "https://cw4sok48swgwsc4skokoook4.37.27.187.127.sslip.io/api/tickets",
							"protocol": "http",
							"host": [
								"localhost"
							],
							"port": "5000",
							"path": [
								"api",
								"tickets"
							]
						}
					},
					"response": []
				},
				{
					"name": "Get Ticket by ID",
					"request": {
						"auth": {
							"type": "bearer",
							"bearer": [
								{
									"key": "token",
									"value": "{{authToken}}",
									"type": "string"
								}
							]
						},
						"method": "GET",
						"header": [],
						"url": {
							"raw": "https://cw4sok48swgwsc4skokoook4.37.27.187.127.sslip.io/api/tickets/{{ticketId}}",
							"protocol": "http",
							"host": [
								"localhost"
							],
							"port": "5000",
							"path": [
								"api",
								"tickets",
								"{{ticketId}}"
							]
						}
					},
					"response": []
				},
				{
					"name": "Update Ticket",
					"request": {
						"auth": {
							"type": "bearer",
							"bearer": [
								{
									"key": "token",
									"value": "{{authToken}}",
									"type": "string"
								}
							]
						},
						"method": "PUT",
						"header": [
							{
								"key": "Content-Type",
								"value": "application/json"
							}
						],
						"body": {
							"mode": "raw",
							"raw": "{\r\n  \"status\": \"Closed\"\r\n}",
							"options": {
								"raw": {
									"language": "json"
								}
							}
						},
						"url": {
							"raw": "https://cw4sok48swgwsc4skokoook4.37.27.187.127.sslip.io/api/tickets/{{68a0a5fec9bf934b442b7774}}/update",
							"protocol": "http",
							"host": [
								"localhost"
							],
							"port": "5000",
							"path": [
								"api",
								"tickets",
								"{{68a0a5fec9bf934b442b7774}}",
								"update"
							]
						}
					},
					"response": []
				}
			]
		},
		{
			"name": "ticket-messages",
			"item": [
				{
					"name": "Send Message",
					"request": {
						"auth": {
							"type": "bearer",
							"bearer": [
								{
									"key": "token",
									"value": "{{authToken}}",
									"type": "string"
								}
							]
						},
						"method": "POST",
						"header": [
							{
								"key": "Content-Type",
								"value": "application/json"
							}
						],
						"body": {
							"mode": "raw",
							"raw": "{\r\n    \"ticketId\":\"68a0a5fec9bf934b442b7774\",\r\n  \"message\": \"سلام، من مشکل را بررسی کردم. لطفاً مراحل زیر را دنبال کنید:\",\r\n  \"attachments\": \"\"\r\n}",
							"options": {
								"raw": {
									"language": "json"
								}
							}
						},
						"url": {
							"raw": "https://cw4sok48swgwsc4skokoook4.37.27.187.127.sslip.io/api/messages/add",
							"protocol": "http",
							"host": [
								"localhost"
							],
							"port": "5000",
							"path": [
								"api",
								"messages",
								"add"
							]
						}
					},
					"response": []
				},
				{
					"name": "Update Message",
					"request": {
						"auth": {
							"type": "bearer",
							"bearer": [
								{
									"key": "token",
									"value": "{{authToken}}",
									"type": "string"
								}
							]
						},
						"method": "PUT",
						"header": [
							{
								"key": "Content-Type",
								"value": "application/json"
							}
						],
						"body": {
							"mode": "raw",
							"raw": "{\r\n  \"message\": \"پیام بروزرسانی شده: لطفاً مشکل را بررسی کنید و راهنمایی کنید.\"\r\n}",
							"options": {
								"raw": {
									"language": "json"
								}
							}
						},
						"url": {
							"raw": "https://cw4sok48swgwsc4skokoook4.37.27.187.127.sslip.io/api/messages/{{messageId}}/update",
							"protocol": "http",
							"host": [
								"localhost"
							],
							"port": "5000",
							"path": [
								"api",
								"messages",
								"{{messageId}}",
								"update"
							]
						}
					},
					"response": []
				}
			]
		},
		{
			"name": "contacts",
			"item": [
				{
					"name": "Create Contact",
					"request": {
						"method": "POST",
						"header": [
							{
								"key": "Content-Type",
								"value": "application/json"
							}
						],
						"body": {
							"mode": "raw",
							"raw": "{\r\n    \"name\": \"علی احمدی\",\r\n    \"email\": \"ali.ahmadi@example.com\",\r\n    \"phone\": \"09123456789\",\r\n    \"subject\": \"درخواست پشتیبانی\",\r\n    \"description\": \"سلام، من در استفاده از سیستم مشکل دارم و نیاز به راهنمایی دارم. لطفاً با من تماس بگیرید.\"\r\n}",
							"options": {
								"raw": {
									"language": "json"
								}
							}
						},
						"url": {
							"raw": "https://cw4sok48swgwsc4skokoook4.37.27.187.127.sslip.io/api/contacts",
							"protocol": "http",
							"host": [
								"localhost"
							],
							"port": "5000",
							"path": [
								"api",
								"contacts"
							]
						}
					},
					"response": []
				},
				{
					"name": "Get All Contacts",
					"request": {
						"auth": {
							"type": "bearer",
							"bearer": [
								{
									"key": "token",
									"value": "{{authToken}}",
									"type": "string"
								}
							]
						},
						"method": "GET",
						"header": [],
						"url": {
							"raw": "https://cw4sok48swgwsc4skokoook4.37.27.187.127.sslip.io/api/contacts?page=1&limit=10&status=new",
							"protocol": "http",
							"host": [
								"localhost"
							],
							"port": "5000",
							"path": [
								"api",
								"contacts"
							],
							"query": [
								{
									"key": "page",
									"value": "1"
								},
								{
									"key": "limit",
									"value": "10"
								},
								{
									"key": "status",
									"value": "new"
								}
							]
						}
					},
					"response": []
				},
				{
					"name": "Get Contact by ID",
					"request": {
						"auth": {
							"type": "bearer",
							"bearer": [
								{
									"key": "token",
									"value": "{{authToken}}",
									"type": "string"
								}
							]
						},
						"method": "GET",
						"header": [],
						"url": {
							"raw": "https://cw4sok48swgwsc4skokoook4.37.27.187.127.sslip.io/api/contacts/{{contactId}}",
							"protocol": "http",
							"host": [
								"localhost"
							],
							"port": "5000",
							"path": [
								"api",
								"contacts",
								"{{contactId}}"
							]
						}
					},
					"response": []
				},
				{
					"name": "Update Contact Status",
					"request": {
						"auth": {
							"type": "bearer",
							"bearer": [
								{
									"key": "token",
									"value": "{{authToken}}",
									"type": "string"
								}
							]
						},
						"method": "PATCH",
						"header": [
							{
								"key": "Content-Type",
								"value": "application/json"
							}
						],
						"body": {
							"mode": "raw",
							"raw": "{\r\n    \"status\": \"answered\"\r\n}",
							"options": {
								"raw": {
									"language": "json"
								}
							}
						},
						"url": {
							"raw": "https://cw4sok48swgwsc4skokoook4.37.27.187.127.sslip.io/api/contacts/{{contactId}}/status",
							"protocol": "http",
							"host": [
								"localhost"
							],
							"port": "5000",
							"path": [
								"api",
								"contacts",
								"{{contactId}}",
								"status"
							]
						}
					},
					"response": []
				},
				{
					"name": "Delete Contact",
					"request": {
						"auth": {
							"type": "bearer",
							"bearer": [
								{
									"key": "token",
									"value": "{{authToken}}",
									"type": "string"
								}
							]
						},
						"method": "DELETE",
						"header": [],
						"url": {
							"raw": "https://cw4sok48swgwsc4skokoook4.37.27.187.127.sslip.io/api/contacts/{{contactId}}",
							"protocol": "http",
							"host": [
								"localhost"
							],
							"port": "5000",
							"path": [
								"api",
								"contacts",
								"{{contactId}}"
							]
						}
					},
					"response": []
				},
				{
					"name": "Get Contact Stats",
					"request": {
						"auth": {
							"type": "bearer",
							"bearer": [
								{
									"key": "token",
									"value": "{{authToken}}",
									"type": "string"
								}
							]
						},
						"method": "GET",
						"header": [],
						"url": {
							"raw": "https://cw4sok48swgwsc4skokoook4.37.27.187.127.sslip.io/api/contacts/stats",
							"protocol": "http",
							"host": [
								"localhost"
							],
							"port": "5000",
							"path": [
								"api",
								"contacts",
								"stats"
							]
						}
					},
					"response": []
				}
			]
		},
		{
			"name": "users",
			"item": [
				{
					"name": "Get All Users",
					"request": {
						"auth": {
							"type": "bearer",
							"bearer": [
								{
									"key": "token",
									"value": "{{authToken}}",
									"type": "string"
								}
							]
						},
						"method": "GET",
						"header": [],
						"url": {
							"raw": "https://cw4sok48swgwsc4skokoook4.37.27.187.127.sslip.io/api/users",
							"protocol": "http",
							"host": [
								"localhost"
							],
							"port": "5000",
							"path": [
								"api",
								"users"
							]
						}
					},
					"response": []
				},
				{
					"name": "Get User by ID",
					"request": {
						"auth": {
							"type": "bearer",
							"bearer": [
								{
									"key": "token",
									"value": "{{authToken}}",
									"type": "string"
								}
							]
						},
						"method": "GET",
						"header": [],
						"url": {
							"raw": "https://cw4sok48swgwsc4skokoook4.37.27.187.127.sslip.io/api/users/{{userId}}",
							"protocol": "http",
							"host": [
								"localhost"
							],
							"port": "5000",
							"path": [
								"api",
								"users",
								"{{userId}}"
							]
						}
					},
					"response": []
				}
			]
		}
	]
}